ivbox/__init__.py
ivbox/orm/SQLiteORM.py
ivbox/orm/__init__.py
ivbox/orm/test.py
ivbox/orm/helpers/QueryResults.py
ivbox/orm/helpers/SchemaValidator.py
ivbox/orm/helpers/__init__.py
ivbox/orm/helpers/utils.py
ivbox/utils/__init__.py
ivbox-0.3.0.dist-info/METADATA
ivbox-0.3.0.dist-info/WHEEL
ivbox-0.3.0.dist-info/top_level.txt
ivbox-0.3.0.dist-info/RECORD
