Metadata-Version: 2.4
Name: ivbox
Version: 0.3.0
Summary: Added utils
Author-email: Ivan Gonzalez <ivanartista96@example.com>
Requires-Python: >=3.10
Requires-Dist: polars
Requires-Dist: pandas
Requires-Dist: numpy
Requires-Dist: requests
Requires-Dist: flet
